[{"continue": 1722, "moves": 4013, "cooperate_at_all": 1447, "continue_at_all": 212, "cooperate": 2059}, {"continue": 2230, "moves": 4508, "cooperate_at_all": 1469, "continue_at_all": 225, "cooperate": 2314}, {"continue": 1068, "moves": 3448, "cooperate_at_all": 1383, "continue_at_all": 140, "cooperate": 1780}, {"continue": 769, "moves": 3186, "cooperate_at_all": 1339, "continue_at_all": 129, "cooperate": 1645}, {"continue": 935, "moves": 3326, "cooperate_at_all": 1296, "continue_at_all": 131, "cooperate": 1635}, {"continue": 525, "moves": 2956, "cooperate_at_all": 1248, "continue_at_all": 69, "cooperate": 1471}, {"continue": 1189, "moves": 3560, "cooperate_at_all": 1286, "continue_at_all": 129, "cooperate": 1843}, {"continue": 267, "moves": 2732, "cooperate_at_all": 1262, "continue_at_all": 35, "cooperate": 1383}, {"continue": 318, "moves": 2793, "cooperate_at_all": 1248, "continue_at_all": 25, "cooperate": 1394}, {"continue": 318, "moves": 2782, "cooperate_at_all": 1298, "continue_at_all": 77, "cooperate": 1410}]