[{"states": {"fc4aa565fc9d553ab3f4c930583a2a": {"action_set": {"high": "defect", "look": true, "low": "defect"}, "strategy_set": {"next": "fc4aa565fc9d553ab3f4c930583a2a"}, "id": "fc4aa565fc9d553ab3f4c930583a2a"}}, "initial_state": "fc4aa565fc9d553ab3f4c930583a2a", "type": 1}, {"states": {"fc4aa565fc9d553ab3f4c930583a2a": {"action_set": {"high": "defect", "look": true, "low": "defect"}, "strategy_set": {"next": "fc4aa565fc9d553ab3f4c930583a2a"}, "id": "fc4aa565fc9d553ab3f4c930583a2a"}}, "initial_state": "fc4aa565fc9d553ab3f4c930583a2a", "type": 1}, {"states": {"fc4aa565fc9d553ab3f4c930583a2a": {"action_set": {"high": "defect", "look": true, "low": "defect"}, "strategy_set": {"next": "fc4aa565fc9d553ab3f4c930583a2a"}, "id": "fc4aa565fc9d553ab3f4c930583a2a"}}, "initial_state": "fc4aa565fc9d553ab3f4c930583a2a", "type": 1}, {"states": {"fc4aa565fc9d553ab3f4c930583a2a": {"action_set": {"high": "defect", "look": true, "low": "defect"}, "strategy_set": {"next": "fc4aa565fc9d553ab3f4c930583a2a"}, "id": "fc4aa565fc9d553ab3f4c930583a2a"}}, "initial_state": "fc4aa565fc9d553ab3f4c930583a2a", "type": 1}, {"states": {"fc4aa565fc9d553ab3f4c930583a2a": {"action_set": {"high": "defect", "look": true, "low": "defect"}, "strategy_set": {"next": "fc4aa565fc9d553ab3f4c930583a2a"}, "id": "fc4aa565fc9d553ab3f4c930583a2a"}}, "initial_state": "fc4aa565fc9d553ab3f4c930583a2a", "type": 1}, {"states": {"fc4aa565fc9d553ab3f4c930583a2a": {"action_set": {"high": "defect", "look": true, "low": "defect"}, "strategy_set": {"next": "fc4aa565fc9d553ab3f4c930583a2a"}, "id": "fc4aa565fc9d553ab3f4c930583a2a"}}, "initial_state": "fc4aa565fc9d553ab3f4c930583a2a", "type": 1}, {"states": {"fc4aa565fc9d553ab3f4c930583a2a": {"action_set": {"high": "defect", "look": true, "low": "defect"}, "strategy_set": {"next": "fc4aa565fc9d553ab3f4c930583a2a"}, "id": "fc4aa565fc9d553ab3f4c930583a2a"}}, "initial_state": "fc4aa565fc9d553ab3f4c930583a2a", "type": 1}, {"states": {"fc4aa565fc9d553ab3f4c930583a2a": {"action_set": {"high": "defect", "look": true, "low": "defect"}, "strategy_set": {"next": "fc4aa565fc9d553ab3f4c930583a2a"}, "id": "fc4aa565fc9d553ab3f4c930583a2a"}}, "initial_state": "fc4aa565fc9d553ab3f4c930583a2a", "type": 1}, {"states": {"fc4aa565fc9d553ab3f4c930583a2a": {"action_set": {"high": "defect", "look": true, "low": "defect"}, "strategy_set": {"next": "fc4aa565fc9d553ab3f4c930583a2a"}, "id": "fc4aa565fc9d553ab3f4c930583a2a"}}, "initial_state": "fc4aa565fc9d553ab3f4c930583a2a", "type": 1}, {"states": {"fc4aa565fc9d553ab3f4c930583a2a": {"action_set": {"high": "defect", "look": true, "low": "defect"}, "strategy_set": {"next": "fc4aa565fc9d553ab3f4c930583a2a"}, "id": "fc4aa565fc9d553ab3f4c930583a2a"}}, "initial_state": "fc4aa565fc9d553ab3f4c930583a2a", "type": 1}, {"states": {"fc4aa565fc9d553ab3f4c930583a2a": {"action_set": {"high": "defect", "look": true, "low": "defect"}, "strategy_set": {"next": "fc4aa565fc9d553ab3f4c930583a2a"}, "id": "fc4aa565fc9d553ab3f4c930583a2a"}}, "initial_state": "fc4aa565fc9d553ab3f4c930583a2a", "type": 1}, {"states": {"fc4aa565fc9d553ab3f4c930583a2a": {"action_set": {"high": "defect", "look": true, "low": "defect"}, "strategy_set": {"next": "fc4aa565fc9d553ab3f4c930583a2a"}, "id": "fc4aa565fc9d553ab3f4c930583a2a"}}, "initial_state": "fc4aa565fc9d553ab3f4c930583a2a", "type": 1}, {"states": {"fc4aa565fc9d553ab3f4c930583a2a": {"action_set": {"high": "defect", "look": true, "low": "defect"}, "strategy_set": {"next": "fc4aa565fc9d553ab3f4c930583a2a"}, "id": "fc4aa565fc9d553ab3f4c930583a2a"}}, "initial_state": "fc4aa565fc9d553ab3f4c930583a2a", "type": 1}, {"states": {"fc4aa565fc9d553ab3f4c930583a2a": {"action_set": {"high": "defect", "look": true, "low": "defect"}, "strategy_set": {"next": "fc4aa565fc9d553ab3f4c930583a2a"}, "id": "fc4aa565fc9d553ab3f4c930583a2a"}}, "initial_state": "fc4aa565fc9d553ab3f4c930583a2a", "type": 1}, {"states": {"fc4aa565fc9d553ab3f4c930583a2a": {"action_set": {"high": "defect", "look": true, "low": "defect"}, "strategy_set": {"next": "25d477b61f6105b2901732c712274d"}, "id": "fc4aa565fc9d553ab3f4c930583a2a"}, "25d477b61f6105b2901732c712274d": {"action_set": {"high": "cooperate", "look": true, "low": "defect"}, "strategy_set": {"next": "25d477b61f6105b2901732c712274d"}, "id": "25d477b61f6105b2901732c712274d"}}, "initial_state": "fc4aa565fc9d553ab3f4c930583a2a", "type": 1}, {"states": {"fc4aa565fc9d553ab3f4c930583a2a": {"action_set": {"high": "defect", "look": true, "low": "defect"}, "strategy_set": {"next": "fc4aa565fc9d553ab3f4c930583a2a"}, "id": "fc4aa565fc9d553ab3f4c930583a2a"}}, "initial_state": "fc4aa565fc9d553ab3f4c930583a2a", "type": 1}, {"states": {"fc4aa565fc9d553ab3f4c930583a2a": {"action_set": {"high": "defect", "look": true, "low": "defect"}, "strategy_set": {"next": "fc4aa565fc9d553ab3f4c930583a2a"}, "id": "fc4aa565fc9d553ab3f4c930583a2a"}}, "initial_state": "fc4aa565fc9d553ab3f4c930583a2a", "type": 1}, {"states": {"fc4aa565fc9d553ab3f4c930583a2a": {"action_set": {"high": "defect", "look": true, "low": "defect"}, "strategy_set": {"next": "fc4aa565fc9d553ab3f4c930583a2a"}, "id": "fc4aa565fc9d553ab3f4c930583a2a"}}, "initial_state": "fc4aa565fc9d553ab3f4c930583a2a", "type": 1}, {"states": {"fc4aa565fc9d553ab3f4c930583a2a": {"action_set": {"high": "defect", "look": true, "low": "defect"}, "strategy_set": {"next": "fc4aa565fc9d553ab3f4c930583a2a"}, "id": "fc4aa565fc9d553ab3f4c930583a2a"}}, "initial_state": "fc4aa565fc9d553ab3f4c930583a2a", "type": 1}, {"states": {"fc4aa565fc9d553ab3f4c930583a2a": {"action_set": {"high": "defect", "look": true, "low": "defect"}, "strategy_set": {"next": "fc4aa565fc9d553ab3f4c930583a2a"}, "id": "fc4aa565fc9d553ab3f4c930583a2a"}}, "initial_state": "fc4aa565fc9d553ab3f4c930583a2a", "type": 1}, {"states": {"fc4aa565fc9d553ab3f4c930583a2a": {"action_set": {"high": "defect", "look": true, "low": "defect"}, "strategy_set": {"next": "fc4aa565fc9d553ab3f4c930583a2a"}, "id": "fc4aa565fc9d553ab3f4c930583a2a"}}, "initial_state": "fc4aa565fc9d553ab3f4c930583a2a", "type": 1}, {"states": {"fc4aa565fc9d553ab3f4c930583a2a": {"action_set": {"high": "defect", "look": true, "low": "defect"}, "strategy_set": {"next": "fc4aa565fc9d553ab3f4c930583a2a"}, "id": "fc4aa565fc9d553ab3f4c930583a2a"}}, "initial_state": "fc4aa565fc9d553ab3f4c930583a2a", "type": 1}, {"states": {"fc4aa565fc9d553ab3f4c930583a2a": {"action_set": {"high": "defect", "look": true, "low": "defect"}, "strategy_set": {"next": "fc4aa565fc9d553ab3f4c930583a2a"}, "id": "fc4aa565fc9d553ab3f4c930583a2a"}}, "initial_state": "fc4aa565fc9d553ab3f4c930583a2a", "type": 1}, {"states": {"fc4aa565fc9d553ab3f4c930583a2a": {"action_set": {"high": "defect", "look": true, "low": "cooperate"}, "strategy_set": {"next": "fc4aa565fc9d553ab3f4c930583a2a"}, "id": "fc4aa565fc9d553ab3f4c930583a2a"}}, "initial_state": "fc4aa565fc9d553ab3f4c930583a2a", "type": 1}, {"states": {"fc4aa565fc9d553ab3f4c930583a2a": {"action_set": {"high": "defect", "look": true, "low": "defect"}, "strategy_set": {"next": "fc4aa565fc9d553ab3f4c930583a2a"}, "id": "fc4aa565fc9d553ab3f4c930583a2a"}}, "initial_state": "fc4aa565fc9d553ab3f4c930583a2a", "type": 1}, {"states": {"fc4aa565fc9d553ab3f4c930583a2a": {"action_set": {"high": "defect", "look": true, "low": "defect"}, "strategy_set": {"next": "fc4aa565fc9d553ab3f4c930583a2a"}, "id": "fc4aa565fc9d553ab3f4c930583a2a"}}, "initial_state": "fc4aa565fc9d553ab3f4c930583a2a", "type": 1}, {"states": {"fc4aa565fc9d553ab3f4c930583a2a": {"action_set": {"high": "defect", "look": true, "low": "defect"}, "strategy_set": {"next": "fc4aa565fc9d553ab3f4c930583a2a"}, "id": "fc4aa565fc9d553ab3f4c930583a2a"}}, "initial_state": "fc4aa565fc9d553ab3f4c930583a2a", "type": 1}, {"states": {"fc4aa565fc9d553ab3f4c930583a2a": {"action_set": {"high": "defect", "look": true, "low": "defect"}, "strategy_set": {"next": "fc4aa565fc9d553ab3f4c930583a2a"}, "id": "fc4aa565fc9d553ab3f4c930583a2a"}}, "initial_state": "fc4aa565fc9d553ab3f4c930583a2a", "type": 1}, {"states": {"fc4aa565fc9d553ab3f4c930583a2a": {"action_set": {"high": "defect", "look": true, "low": "defect"}, "strategy_set": {"next": "fc4aa565fc9d553ab3f4c930583a2a"}, "id": "fc4aa565fc9d553ab3f4c930583a2a"}}, "initial_state": "fc4aa565fc9d553ab3f4c930583a2a", "type": 1}, {"states": {"fc4aa565fc9d553ab3f4c930583a2a": {"action_set": {"high": "defect", "look": true, "low": "defect"}, "strategy_set": {"next": "fc4aa565fc9d553ab3f4c930583a2a"}, "id": "fc4aa565fc9d553ab3f4c930583a2a"}}, "initial_state": "fc4aa565fc9d553ab3f4c930583a2a", "type": 1}, {"states": {"fc4aa565fc9d553ab3f4c930583a2a": {"action_set": {"high": "defect", "look": true, "low": "defect"}, "strategy_set": {"next": "fc4aa565fc9d553ab3f4c930583a2a"}, "id": "fc4aa565fc9d553ab3f4c930583a2a"}}, "initial_state": "fc4aa565fc9d553ab3f4c930583a2a", "type": 1}, {"states": {"fc4aa565fc9d553ab3f4c930583a2a": {"action_set": {"high": "defect", "look": true, "low": "defect"}, "strategy_set": {"next": "25d477b61f6105b2901732c712274d"}, "id": "fc4aa565fc9d553ab3f4c930583a2a"}, "25d477b61f6105b2901732c712274d": {"action_set": {"high": "cooperate", "look": true, "low": "defect"}, "strategy_set": {"next": "25d477b61f6105b2901732c712274d"}, "id": "25d477b61f6105b2901732c712274d"}}, "initial_state": "fc4aa565fc9d553ab3f4c930583a2a", "type": 1}, {"states": {"fc4aa565fc9d553ab3f4c930583a2a": {"action_set": {"high": "defect", "look": true, "low": "defect"}, "strategy_set": {"next": "fc4aa565fc9d553ab3f4c930583a2a"}, "id": "fc4aa565fc9d553ab3f4c930583a2a"}}, "initial_state": "fc4aa565fc9d553ab3f4c930583a2a", "type": 1}, {"states": {"fc4aa565fc9d553ab3f4c930583a2a": {"action_set": {"high": "defect", "look": true, "low": "defect"}, "strategy_set": {"next": "25d477b61f6105b2901732c712274d"}, "id": "fc4aa565fc9d553ab3f4c930583a2a"}, "25d477b61f6105b2901732c712274d": {"action_set": {"high": "cooperate", "look": true, "low": "defect"}, "strategy_set": {"next": "25d477b61f6105b2901732c712274d"}, "id": "25d477b61f6105b2901732c712274d"}}, "initial_state": "fc4aa565fc9d553ab3f4c930583a2a", "type": 1}, {"states": {"fc4aa565fc9d553ab3f4c930583a2a": {"action_set": {"high": "defect", "look": true, "low": "defect"}, "strategy_set": {"next": "fc4aa565fc9d553ab3f4c930583a2a"}, "id": "fc4aa565fc9d553ab3f4c930583a2a"}}, "initial_state": "fc4aa565fc9d553ab3f4c930583a2a", "type": 1}, {"states": {"fc4aa565fc9d553ab3f4c930583a2a": {"action_set": {"high": "defect", "look": true, "low": "defect"}, "strategy_set": {"next": "fc4aa565fc9d553ab3f4c930583a2a"}, "id": "fc4aa565fc9d553ab3f4c930583a2a"}}, "initial_state": "fc4aa565fc9d553ab3f4c930583a2a", "type": 1}, {"states": {"fc4aa565fc9d553ab3f4c930583a2a": {"action_set": {"high": "defect", "look": true, "low": "defect"}, "strategy_set": {"next": "fc4aa565fc9d553ab3f4c930583a2a"}, "id": "fc4aa565fc9d553ab3f4c930583a2a"}}, "initial_state": "fc4aa565fc9d553ab3f4c930583a2a", "type": 1}, {"states": {"fc4aa565fc9d553ab3f4c930583a2a": {"action_set": {"high": "defect", "look": true, "low": "defect"}, "strategy_set": {"next": "fc4aa565fc9d553ab3f4c930583a2a"}, "id": "fc4aa565fc9d553ab3f4c930583a2a"}}, "initial_state": "fc4aa565fc9d553ab3f4c930583a2a", "type": 1}, {"states": {"fc4aa565fc9d553ab3f4c930583a2a": {"action_set": {"high": "defect", "look": true, "low": "defect"}, "strategy_set": {"next": "fc4aa565fc9d553ab3f4c930583a2a"}, "id": "fc4aa565fc9d553ab3f4c930583a2a"}}, "initial_state": "fc4aa565fc9d553ab3f4c930583a2a", "type": 1}, {"states": {"fc4aa565fc9d553ab3f4c930583a2a": {"action_set": {"high": "defect", "look": true, "low": "defect"}, "strategy_set": {"next": "fc4aa565fc9d553ab3f4c930583a2a"}, "id": "fc4aa565fc9d553ab3f4c930583a2a"}}, "initial_state": "fc4aa565fc9d553ab3f4c930583a2a", "type": 1}, {"states": {"fc4aa565fc9d553ab3f4c930583a2a": {"action_set": {"high": "defect", "look": true, "low": "defect"}, "strategy_set": {"next": "fc4aa565fc9d553ab3f4c930583a2a"}, "id": "fc4aa565fc9d553ab3f4c930583a2a"}}, "initial_state": "fc4aa565fc9d553ab3f4c930583a2a", "type": 1}, {"states": {"fc4aa565fc9d553ab3f4c930583a2a": {"action_set": {"high": "defect", "look": true, "low": "defect"}, "strategy_set": {"next": "fc4aa565fc9d553ab3f4c930583a2a"}, "id": "fc4aa565fc9d553ab3f4c930583a2a"}}, "initial_state": "fc4aa565fc9d553ab3f4c930583a2a", "type": 1}, {"states": {"fc4aa565fc9d553ab3f4c930583a2a": {"action_set": {"high": "defect", "look": true, "low": "defect"}, "strategy_set": {"next": "fc4aa565fc9d553ab3f4c930583a2a"}, "id": "fc4aa565fc9d553ab3f4c930583a2a"}}, "initial_state": "fc4aa565fc9d553ab3f4c930583a2a", "type": 1}, {"states": {"fc4aa565fc9d553ab3f4c930583a2a": {"action_set": {"high": "defect", "look": true, "low": "defect"}, "strategy_set": {"next": "fc4aa565fc9d553ab3f4c930583a2a"}, "id": "fc4aa565fc9d553ab3f4c930583a2a"}}, "initial_state": "fc4aa565fc9d553ab3f4c930583a2a", "type": 1}, {"states": {"fc4aa565fc9d553ab3f4c930583a2a": {"action_set": {"high": "defect", "look": true, "low": "defect"}, "strategy_set": {"next": "fc4aa565fc9d553ab3f4c930583a2a"}, "id": "fc4aa565fc9d553ab3f4c930583a2a"}}, "initial_state": "fc4aa565fc9d553ab3f4c930583a2a", "type": 1}, {"states": {"fc4aa565fc9d553ab3f4c930583a2a": {"action_set": {"high": "defect", "look": true, "low": "defect"}, "strategy_set": {"next": "fc4aa565fc9d553ab3f4c930583a2a"}, "id": "fc4aa565fc9d553ab3f4c930583a2a"}}, "initial_state": "fc4aa565fc9d553ab3f4c930583a2a", "type": 1}, {"states": {"fc4aa565fc9d553ab3f4c930583a2a": {"action_set": {"high": "defect", "look": true, "low": "defect"}, "strategy_set": {"next": "fc4aa565fc9d553ab3f4c930583a2a"}, "id": "fc4aa565fc9d553ab3f4c930583a2a"}}, "initial_state": "fc4aa565fc9d553ab3f4c930583a2a", "type": 1}, {"states": {"fc4aa565fc9d553ab3f4c930583a2a": {"action_set": {"high": "defect", "look": true, "low": "defect"}, "strategy_set": {"next": "fc4aa565fc9d553ab3f4c930583a2a"}, "id": "fc4aa565fc9d553ab3f4c930583a2a"}}, "initial_state": "fc4aa565fc9d553ab3f4c930583a2a", "type": 1}, {"states": {"fc4aa565fc9d553ab3f4c930583a2a": {"action_set": {"high": "defect", "look": true, "low": "defect"}, "strategy_set": {"next": "fc4aa565fc9d553ab3f4c930583a2a"}, "id": "fc4aa565fc9d553ab3f4c930583a2a"}}, "initial_state": "fc4aa565fc9d553ab3f4c930583a2a", "type": 1}, {"states": {"fc4aa565fc9d553ab3f4c930583a2a": {"action_set": {"high": "defect", "look": true, "low": "defect"}, "strategy_set": {"next": "fc4aa565fc9d553ab3f4c930583a2a"}, "id": "fc4aa565fc9d553ab3f4c930583a2a"}}, "initial_state": "fc4aa565fc9d553ab3f4c930583a2a", "type": 1}]